versioninfo/__init__.py
versioninfo/exceptions.py
versioninfo/parser.py
versioninfo-1.1.2.dist-info/LICENSE.txt
versioninfo-1.1.2.dist-info/METADATA
versioninfo-1.1.2.dist-info/WHEEL
versioninfo-1.1.2.dist-info/top_level.txt
versioninfo-1.1.2.dist-info/zip-safe
versioninfo-1.1.2.dist-info/RECORD
