Metadata-Version: 2.1
Name: versioninfo
Version: 1.1.2
Summary: Parse PE VS_VERSIONINFO structure and return JSON string.
Home-page: https://github.com/malwarology/versioninfo
Author: Malwarology LLC
Project-URL: Bug Tracker, https://github.com/malwarology/versioninfo/issues
Classifier: Development Status :: 4 - Beta
Classifier: Intended Audience :: Developers
Classifier: Intended Audience :: Information Technology
Classifier: Intended Audience :: System Administrators
Classifier: License :: OSI Approved :: MIT License
Classifier: Natural Language :: English
Classifier: Operating System :: OS Independent
Classifier: Programming Language :: Python
Classifier: Programming Language :: Python :: 3
Classifier: Programming Language :: Python :: 3 :: Only
Classifier: Programming Language :: Python :: 3.11
Classifier: Topic :: Security
Classifier: Topic :: Software Development
Classifier: Topic :: Software Development :: Libraries
Classifier: Topic :: Software Development :: Libraries :: Python Modules
Classifier: Topic :: System :: Systems Administration
Classifier: Topic :: Utilities
Requires-Python: >=3.11.0
License-File: LICENSE.txt
